<?xml version="1.0" encoding="ISO-8859-1"?>
<modeling>
 <generator>
  <i name="program" type="string">vasp </i>
  <i name="version" type="string">5.4.4.18Apr17-6-g9f103f2a35  </i>
  <i name="subversion" type="string">(build Dec 09 2018 21:25:21) complex            parallel </i>
  <i name="platform" type="string">IFC18.0.1.163_CrayMPICH7.7.0_MKL18.0.1.163 </i>
  <i name="date" type="string">2019 03 20 </i>
  <i name="time" type="string">09:13:06 </i>
 </generator>
 <incar>
  <i type="string" name="PREC">normal</i>
  <i type="int" name="IBRION">     2</i>
  <i name="EDIFF">      0.00040000</i>
  <i name="EDIFFG">     -0.01000000</i>
  <i type="int" name="NSW">    15</i>
  <i type="int" name="ISIF">     3</i>
  <i name="ENCUT">    200.00000000</i>
  <i type="int" name="NBANDS">     8</i>
  <i type="logical" name="LREAL"> F  </i>
  <i type="int" name="ISMEAR">     0</i>
  <i name="SIGMA">      0.20000000</i>
  <v type="int" name="KPOINT_BSE">    -1     0     0     0</v>
 </incar>
 <structure name="primitive_cell" >
  <crystal>
   <varray name="basis" >
    <v>      -2.45000000       2.45000000       1.27400000 </v>
    <v>       2.45000000      -2.45000000       1.27400000 </v>
    <v>       2.45000000       2.45000000      -1.27400000 </v>
   </varray>
   <i name="volume">     30.58874000 </i>
   <varray name="rec_basis" >
    <v>       0.00000000       0.20408163       0.39246468 </v>
    <v>       0.20408163       0.00000000       0.39246468 </v>
    <v>       0.20408163       0.20408163      -0.00000000 </v>
   </varray>
  </crystal>
  <varray name="positions" >
   <v>       0.25000000      -0.25000000      -0.50000000 </v>
   <v>       0.00000000       0.00000000       0.00000000 </v>
  </varray>
 </structure>
 <varray name="primitive_index" >
  <v type="int" >        1 </v>
  <v type="int" >        2 </v>
 </varray>
 <kpoints>
  <generation param="Monkhorst-Pack">
   <v type="int" name="divisions">       2        2        2 </v>
   <v name="usershift">      0.00000000       0.00000000       0.00000000 </v>
   <v name="genvec1">      0.50000000       0.00000000      -0.00000000 </v>
   <v name="genvec2">      0.00000000       0.50000000      -0.00000000 </v>
   <v name="genvec3">      0.00000000      -0.00000000       0.50000000 </v>
   <v name="shift">      0.50000000       0.50000000       0.50000000 </v>
  </generation>
  <varray name="kpointlist" >
   <v>       0.25000000       0.25000000       0.25000000 </v>
   <v>      -0.25000000       0.25000000       0.25000000 </v>
   <v>      -0.25000000      -0.25000000       0.25000000 </v>
  </varray>
  <varray name="weights" >
   <v>       0.25000000 </v>
   <v>       0.50000000 </v>
   <v>       0.25000000 </v>
  </varray>
 </kpoints>
 <parameters>
  <separator name="general" >
   <i type="string" name="SYSTEM">unknown system</i>
   <i type="logical" name="LCOMPAT"> F  </i>
  </separator>
  <separator name="electronic" >
   <i type="string" name="PREC">normal</i>
   <i name="ENMAX">    200.00000000</i>
   <i name="ENAUG">    322.06900000</i>
   <i name="EDIFF">      0.00040000</i>
   <i type="int" name="IALGO">    38</i>
   <i type="int" name="IWAVPR">    11</i>
   <i type="int" name="NBANDS">     8</i>
   <i name="NELECT">      8.00000000</i>
   <i type="int" name="TURBO">     0</i>
   <i type="int" name="IRESTART">     0</i>
   <i type="int" name="NREBOOT">     0</i>
   <i type="int" name="NMIN">     0</i>
   <i name="EREF">      0.00000000</i>
   <separator name="electronic smearing" >
    <i type="int" name="ISMEAR">     0</i>
    <i name="SIGMA">      0.20000000</i>
    <i name="KSPACING">      0.50000000</i>
    <i type="logical" name="KGAMMA"> T  </i>
   </separator>
   <separator name="electronic projectors" >
    <i type="logical" name="LREAL"> F  </i>
    <v name="ROPT">      0.00000000</v>
    <i type="int" name="LMAXPAW">  -100</i>
    <i type="int" name="LMAXMIX">     2</i>
    <i type="logical" name="NLSPLINE"> F  </i>
   </separator>
   <separator name="electronic startup" >
    <i type="int" name="ISTART">     0</i>
    <i type="int" name="ICHARG">     2</i>
    <i type="int" name="INIWAV">     1</i>
   </separator>
   <separator name="electronic spin" >
    <i type="int" name="ISPIN">     1</i>
    <i type="logical" name="LNONCOLLINEAR"> F  </i>
    <v name="MAGMOM">      1.00000000      1.00000000</v>
    <i name="NUPDOWN">     -1.00000000</i>
    <i type="logical" name="LSORBIT"> F  </i>
    <v name="SAXIS">      0.00000000      0.00000000      1.00000000</v>
    <i type="logical" name="LSPIRAL"> F  </i>
    <v name="QSPIRAL">      0.00000000      0.00000000      0.00000000</v>
    <i type="logical" name="LZEROZ"> F  </i>
   </separator>
   <separator name="electronic exchange-correlation" >
    <i type="logical" name="LASPH"> F  </i>
    <i type="logical" name="LMETAGGA"> F  </i>
   </separator>
   <separator name="electronic convergence" >
    <i type="int" name="NELM">    60</i>
    <i type="int" name="NELMDL">    -5</i>
    <i type="int" name="NELMIN">     2</i>
    <i name="ENINI">    200.00000000</i>
    <separator name="electronic convergence detail" >
     <i type="logical" name="LDIAG"> T  </i>
     <i type="logical" name="LSUBROT"> F  </i>
     <i name="WEIMIN">      0.00100000</i>
     <i name="EBREAK">      0.00001250</i>
     <i name="DEPER">      0.30000000</i>
     <i type="int" name="NRMM">     4</i>
     <i name="TIME">      0.40000000</i>
    </separator>
   </separator>
   <separator name="electronic mixer" >
    <i name="AMIX">      0.40000000</i>
    <i name="BMIX">      1.00000000</i>
    <i name="AMIN">      0.10000000</i>
    <i name="AMIX_MAG">      1.60000000</i>
    <i name="BMIX_MAG">      1.00000000</i>
    <separator name="electronic mixer details" >
     <i type="int" name="IMIX">     4</i>
     <i type="logical" name="MIXFIRST"> F  </i>
     <i type="int" name="MAXMIX">   -45</i>
     <i name="WC">    100.00000000</i>
     <i type="int" name="INIMIX">     1</i>
     <i type="int" name="MIXPRE">     1</i>
     <i type="int" name="MREMOVE">     5</i>
    </separator>
   </separator>
   <separator name="electronic dipolcorrection" >
    <i type="logical" name="LDIPOL"> F  </i>
    <i type="logical" name="LMONO"> F  </i>
    <i type="int" name="IDIPOL">     0</i>
    <i name="EPSILON">      1.00000000</i>
    <v name="DIPOL">   -100.00000000   -100.00000000   -100.00000000</v>
    <i name="EFIELD">      0.00000000</i>
   </separator>
  </separator>
  <separator name="grids" >
   <i type="int" name="NGX">    14</i>
   <i type="int" name="NGY">    14</i>
   <i type="int" name="NGZ">    14</i>
   <i type="int" name="NGXF">    28</i>
   <i type="int" name="NGYF">    28</i>
   <i type="int" name="NGZF">    28</i>
   <i type="logical" name="ADDGRID"> F  </i>
  </separator>
  <separator name="ionic" >
   <i type="int" name="NSW">    15</i>
   <i type="int" name="IBRION">     2</i>
   <i type="int" name="MDALGO">     0</i>
   <i type="int" name="ISIF">     3</i>
   <i name="PSTRESS">      0.00000000</i>
   <i name="EDIFFG">     -0.01000000</i>
   <i type="int" name="NFREE">     1</i>
   <i name="POTIM">      0.50000000</i>
   <i name="SMASS">     -3.00000000</i>
   <i name="SCALEE">      1.00000000</i>
  </separator>
  <separator name="ionic md" >
   <i name="TEBEG">      0.00010000</i>
   <i name="TEEND">      0.00010000</i>
   <i type="int" name="NBLOCK">     1</i>
   <i type="int" name="KBLOCK">    15</i>
   <i type="int" name="NPACO">   256</i>
   <i name="APACO">     16.00000000</i>
  </separator>
  <separator name="symmetry" >
   <i type="int" name="ISYM">     2</i>
   <i name="SYMPREC">      0.00001000</i>
  </separator>
  <separator name="dos" >
   <i type="int" name="LORBIT">     0</i>
   <v name="RWIGS">     -1.00000000</v>
   <i type="int" name="NEDOS">   301</i>
   <i name="EMIN">     10.00000000</i>
   <i name="EMAX">    -10.00000000</i>
   <i name="EFERMI">      0.00000000</i>
  </separator>
  <separator name="writing" >
   <i type="int" name="NWRITE">     2</i>
   <i type="logical" name="LWAVE"> T  </i>
   <i type="logical" name="LDOWNSAMPLE"> F  </i>
   <i type="logical" name="LCHARG"> T  </i>
   <i type="logical" name="LPARD"> F  </i>
   <i type="logical" name="LVTOT"> F  </i>
   <i type="logical" name="LVHAR"> F  </i>
   <i type="logical" name="LELF"> F  </i>
   <i type="logical" name="LOPTICS"> F  </i>
   <v name="STM">      0.00000000      0.00000000      0.00000000      0.00000000      0.00000000      0.00000000      0.00000000</v>
  </separator>
  <separator name="performance" >
   <i type="int" name="NPAR">     8</i>
   <i type="int" name="NSIM">     4</i>
   <i type="int" name="NBLK">    -1</i>
   <i type="logical" name="LPLANE"> T  </i>
   <i type="logical" name="LSCALAPACK"> T  </i>
   <i type="logical" name="LSCAAWARE"> F  </i>
   <i type="logical" name="LSCALU"> F  </i>
   <i type="logical" name="LASYNC"> F  </i>
   <i type="logical" name="LORBITALREAL"> F  </i>
  </separator>
  <separator name="miscellaneous" >
   <i type="int" name="IDIOT">     3</i>
   <i type="int" name="ISPECIAL">     0</i>
   <i type="logical" name="LMUSIC"> F  </i>
   <v name="POMASS">     28.08500000</v>
   <v name="DARWINR">      0.00000000</v>
   <v name="DARWINV">      1.00000000</v>
   <i type="logical" name="LCORR"> T  </i>
  </separator>
  <i type="logical" name="GGA_COMPAT"> T  </i>
  <i type="logical" name="LBERRY"> F  </i>
  <i type="int" name="ICORELEVEL">     0</i>
  <i type="logical" name="LDAU"> F  </i>
  <i type="int" name="I_CONSTRAINED_M">     0</i>
  <separator name="electronic exchange-correlation" >
   <i type="string" name="GGA">--</i>
   <i type="int" name="VOSKOWN">     0</i>
   <i type="logical" name="LHFCALC"> F  </i>
   <i type="string" name="PRECFOCK"></i>
   <i type="logical" name="LSYMGRAD"> F  </i>
   <i type="logical" name="LHFONE"> F  </i>
   <i type="logical" name="LRHFCALC"> F  </i>
   <i type="logical" name="LTHOMAS"> F  </i>
   <i type="logical" name="LMODELHF"> F  </i>
   <i name="ENCUT4O">     -1.00000000</i>
   <i type="int" name="EXXOEP">     0</i>
   <i type="int" name="FOURORBIT">     0</i>
   <i name="AEXX">      0.00000000</i>
   <i name="HFALPHA">      0.00000000</i>
   <i name="MCALPHA">      0.00000000</i>
   <i name="ALDAX">      1.00000000</i>
   <i name="AGGAX">      1.00000000</i>
   <i name="ALDAC">      1.00000000</i>
   <i name="AGGAC">      1.00000000</i>
   <i type="int" name="NKREDX">     1</i>
   <i type="int" name="NKREDY">     1</i>
   <i type="int" name="NKREDZ">     1</i>
   <i type="logical" name="SHIFTRED"> F  </i>
   <i type="logical" name="ODDONLY"> F  </i>
   <i type="logical" name="EVENONLY"> F  </i>
   <i type="int" name="LMAXFOCK">     0</i>
   <i type="int" name="NMAXFOCKAE">     0</i>
   <i type="logical" name="LFOCKAEDFT"> F  </i>
   <i name="HFSCREEN">      0.00000000</i>
   <i name="HFSCREENC">      0.00000000</i>
   <i type="int" name="NBANDSGWLOW">     0</i>
  </separator>
  <separator name="vdW DFT" >
   <i type="logical" name="LUSE_VDW"> F  </i>
   <i name="Zab_VDW">     -0.84910000</i>
   <i name="PARAM1">      0.12340000</i>
   <i name="PARAM2">      1.00000000</i>
   <i name="PARAM3">      0.00000000</i>
  </separator>
  <separator name="model GW" >
   <i type="int" name="MODEL_GW">     0</i>
   <i name="MODEL_EPS0">      9.17662200</i>
   <i name="MODEL_ALPHA">      1.00000000</i>
  </separator>
  <separator name="linear response parameters" >
   <i type="logical" name="LEPSILON"> F  </i>
   <i type="logical" name="LRPA"> F  </i>
   <i type="logical" name="LNABLA"> F  </i>
   <i type="logical" name="LVEL"> F  </i>
   <i type="int" name="KINTER">     0</i>
   <i name="CSHIFT">      0.10000000</i>
   <i name="OMEGAMAX">     -1.00000000</i>
   <i name="DEG_THRESHOLD">      0.00200000</i>
   <i name="RTIME">     -0.10000000</i>
   <i name="WPLASMAI">      0.00000000</i>
   <v name="DFIELD">      0.00000000      0.00000000      0.00000000</v>
   <v name="WPLASMA">      0.00000000      0.00000000      0.00000000      0.00000000      0.00000000      0.00000000      0.00000000      0.00000000      0.00000000</v>
  </separator>
  <separator name="orbital magnetization" >
   <i type="logical" name="NUCIND"> F  </i>
   <v name="MAGPOS">      0.00000000      0.00000000      0.00000000</v>
   <i type="logical" name="LNICSALL"> T  </i>
   <i type="logical" name="ORBITALMAG"> F  </i>
   <i type="logical" name="LMAGBLOCH"> F  </i>
   <i type="logical" name="LCHIMAG"> F  </i>
   <i type="logical" name="LGAUGE"> T  </i>
   <i type="int" name="MAGATOM">     0</i>
   <v name="MAGDIPOL">      0.00000000      0.00000000      0.00000000</v>
   <v name="AVECCONST">      0.00000000      0.00000000      0.00000000</v>
  </separator>
  <separator name="response functions" >
   <i type="logical" name="LADDER"> F  </i>
   <i type="logical" name="LRPAFORCE"> F  </i>
   <i type="logical" name="LFXC"> F  </i>
   <i type="logical" name="LHARTREE"> T  </i>
   <i type="int" name="IBSE">     0</i>
   <v type="int" name="KPOINT">    -1     0     0     0</v>
   <i type="logical" name="LTCTE"> F  </i>
   <i type="logical" name="LTETE"> F  </i>
   <i type="logical" name="LTRIPLET"> F  </i>
   <i type="logical" name="LFXCEPS"> F  </i>
   <i type="logical" name="LFXHEG"> F  </i>
   <i type="int" name="NATURALO">     2</i>
   <i type="logical" name="L2ORDER"> F  </i>
   <i type="logical" name="LMP2LT"> F  </i>
   <i type="logical" name="LUSEW"> F  </i>
   <i name="ENCUTGW">     -2.00000000</i>
   <i name="ENCUTGWSOFT">     -2.00000000</i>
   <i name="ENCUTLF">     -1.00000000</i>
   <i type="int" name="LMAXMP2">    -1</i>
   <i name="SCISSOR">      0.00000000</i>
   <i type="int" name="NOMEGA">     0</i>
   <i type="int" name="NOMEGAR">     0</i>
   <i type="int" name="NBANDSGW">    -1</i>
   <i type="int" name="NBANDSO">    -1</i>
   <i type="int" name="NBANDSV">    -1</i>
   <i type="int" name="NELM">     1</i>
   <i type="int" name="NELMHF">     1</i>
   <i type="int" name="DIM">     3</i>
   <i type="int" name="ANTIRES">     0</i>
   <i name="OMEGAMAX">    -30.00000000</i>
   <i name="OMEGAMIN">    -30.00000000</i>
   <i name="OMEGATL">   -200.00000000</i>
   <i type="int" name="OMEGAGRID">   140</i>
   <i name="CSHIFT">     -0.10000000</i>
   <i type="logical" name="SELFENERGY"> F  </i>
   <i type="logical" name="LSPECTRAL"> F  </i>
   <i type="logical" name="LSPECTRALGW"> F  </i>
   <i type="logical" name="LSINGLES"> F  </i>
   <i type="logical" name="LFERMIGW"> F  </i>
   <i type="logical" name="ODDONLYGW"> F  </i>
   <i type="logical" name="EVENONLYGW"> F  </i>
   <i type="int" name="NKREDLFX">     1</i>
   <i type="int" name="NKREDLFY">     1</i>
   <i type="int" name="NKREDLFZ">     1</i>
   <i type="int" name="MAXMEM">  2800</i>
   <i type="int" name="TELESCOPE">     0</i>
   <i type="int" name="TAUPAR">     1</i>
   <i type="int" name="OMEGAPAR">    -1</i>
   <i name="LAMBDA">      1.00000000</i>
  </separator>
  <separator name="External order field" >
   <i name="OFIELD_KAPPA">      0.00000000</i>
   <v name="OFIELD_K">      0.00000000      0.00000000      0.00000000</v>
   <i name="OFIELD_Q6_NEAR">      0.00000000</i>
   <i name="OFIELD_Q6_FAR">      0.00000000</i>
   <i name="OFIELD_A">      0.00000000</i>
  </separator>
 </parameters>
 <atominfo>
  <atoms>       2 </atoms>
  <types>       1 </types>
  <array name="atoms" >
   <dimension dim="1">ion</dimension>
   <field type="string">element</field>
   <field type="int">atomtype</field>
   <set>
    <rc><c>Si</c><c>   1</c></rc>
    <rc><c>Si</c><c>   1</c></rc>
   </set>
  </array>
  <array name="atomtypes" >
   <dimension dim="1">type</dimension>
   <field type="int">atomspertype</field>
   <field type="string">element</field>
   <field>mass</field>
   <field>valence</field>
   <field type="string">pseudopotential</field>
   <set>
    <rc><c>   2</c><c>Si</c><c>     28.08500000</c><c>      4.00000000</c><c> PAW_PBE Si 05Jan2001                   </c></rc>
   </set>
  </array>
 </atominfo>
 <structure name="initialpos" >
  <crystal>
   <varray name="basis" >
    <v>      -2.45000000       2.45000000       1.27400000 </v>
    <v>       2.45000000      -2.45000000       1.27400000 </v>
    <v>       2.45000000       2.45000000      -1.27400000 </v>
   </varray>
   <i name="volume">     30.58874000 </i>
   <varray name="rec_basis" >
    <v>       0.00000000       0.20408163       0.39246468 </v>
    <v>       0.20408163       0.00000000       0.39246468 </v>
    <v>       0.20408163       0.20408163      -0.00000000 </v>
   </varray>
  </crystal>
  <varray name="positions" >
   <v>       0.25000000       0.75000000       0.50000000 </v>
   <v>       0.00000000       0.00000000       0.00000000 </v>
  </varray>
 </structure>
 <calculation>
  <scstep>
   <time name="dav">    0.03    0.03</time>
   <time name="total">    0.06    0.07</time>
   <energy>
    <i name="alphaZ">      4.40202223 </i>
    <i name="ewald">   -265.18101312 </i>
    <i name="hartreedc">     -2.30415367 </i>
    <i name="XCdc">    -17.81545108 </i>
    <i name="pawpsdc">     65.95520812 </i>
    <i name="pawaedc">    -30.76852678 </i>
    <i name="eentropy">     -0.05641896 </i>
    <i name="bandstr">     35.89214471 </i>
    <i name="atom">    206.11247263 </i>
    <i name="e_fr_energy">     -3.76371592 </i>
    <i name="e_wo_entrp">     -3.70729696 </i>
    <i name="e_0_energy">     -3.73550644 </i>
   </energy>
  </scstep>
  <scstep>
   <time name="dav">    0.04    0.06</time>
   <time name="total">    0.04    0.06</time>
   <energy>
    <i name="e_fr_energy">    -11.94962114 </i>
    <i name="e_wo_entrp">    -11.89320218 </i>
    <i name="e_0_energy">    -11.92141166 </i>
   </energy>
  </scstep>
  <scstep>
   <time name="dav">    0.04    0.04</time>
   <time name="total">    0.04    0.05</time>
   <energy>
    <i name="e_fr_energy">    -12.00727348 </i>
    <i name="e_wo_entrp">    -11.95085453 </i>
    <i name="e_0_energy">    -11.97906400 </i>
   </energy>
  </scstep>
  <scstep>
   <time name="dav">    0.04    0.04</time>
   <time name="total">    0.04    0.04</time>
   <energy>
    <i name="e_fr_energy">    -12.00733987 </i>
    <i name="e_wo_entrp">    -11.95092091 </i>
    <i name="e_0_energy">    -11.97913039 </i>
   </energy>
  </scstep>
  <scstep>
   <time name="dav">    0.03    0.03</time>
   <time name="total">    0.04    0.05</time>
   <energy>
    <i name="e_fr_energy">    -12.00733995 </i>
    <i name="e_wo_entrp">    -11.95092099 </i>
    <i name="e_0_energy">    -11.97913047 </i>
   </energy>
  </scstep>
  <scstep>
   <time name="dav">    0.03    0.03</time>
   <time name="total">    0.06    0.07</time>
   <energy>
    <i name="e_fr_energy">    -11.99465593 </i>
    <i name="e_wo_entrp">    -11.93823697 </i>
    <i name="e_0_energy">    -11.96644645 </i>
   </energy>
  </scstep>
  <scstep>
   <time name="dav">    0.02    0.02</time>
   <time name="total">    0.06    0.06</time>
   <energy>
    <i name="e_fr_energy">    -11.98644850 </i>
    <i name="e_wo_entrp">    -11.93002955 </i>
    <i name="e_0_energy">    -11.95823903 </i>
   </energy>
  </scstep>
  <scstep>
   <time name="dav">    0.03    0.03</time>
   <time name="total">    0.06    0.06</time>
   <energy>
    <i name="alphaZ">      4.40202223 </i>
    <i name="ewald">   -265.18101312 </i>
    <i name="hartreedc">     -2.25136873 </i>
    <i name="XCdc">    -17.60448244 </i>
    <i name="pawpsdc">     70.78036611 </i>
    <i name="pawaedc">    -35.67935936 </i>
    <i name="eentropy">     -0.05641896 </i>
    <i name="bandstr">     27.49137482 </i>
    <i name="atom">    206.11247263 </i>
    <i name="e_fr_energy">    -11.98640682 </i>
    <i name="e_wo_entrp">    -11.92998786 </i>
    <i name="e_0_energy">    -11.95819734 </i>
   </energy>
  </scstep>
  <structure>
   <crystal>
    <varray name="basis" >
     <v>      -2.45000000       2.45000000       1.27400000 </v>
     <v>       2.45000000      -2.45000000       1.27400000 </v>
     <v>       2.45000000       2.45000000      -1.27400000 </v>
    </varray>
    <i name="volume">     30.58874000 </i>
    <varray name="rec_basis" >
     <v>       0.00000000       0.20408163       0.39246468 </v>
     <v>       0.20408163       0.00000000       0.39246468 </v>
     <v>       0.20408163       0.20408163      -0.00000000 </v>
    </varray>
   </crystal>
   <varray name="positions" >
    <v>       0.25000000       0.75000000       0.50000000 </v>
    <v>       0.00000000       0.00000000       0.00000000 </v>
   </varray>
  </structure>
  <varray name="forces" >
   <v>       0.00000000       0.00000000       0.00000000 </v>
   <v>      -0.00000000      -0.00000000      -0.00000000 </v>
  </varray>
  <varray name="stress" >
   <v>    -236.25745055       0.00000000       0.00000000 </v>
   <v>       0.00000000    -236.25745055      -0.00000000 </v>
   <v>       0.00000000      -0.00000000     238.36219362 </v>
  </varray>
  <energy>
   <i name="e_fr_energy">    -11.98640682 </i>
   <i name="e_wo_entrp">    -11.95819734 </i>
   <i name="e_0_energy">     -0.05641896 </i>
  </energy>
  <time name="totalsc">    0.97    1.30</time>
 </calculation>
 <calculation>
  <scstep>
   <time name="dav">    0.02    0.02</time>
   <time name="total">    0.06    0.06</time>
   <energy>
    <i name="alphaZ">      4.99425214 </i>
    <i name="ewald">   -275.22881378 </i>
    <i name="hartreedc">     -2.25202096 </i>
    <i name="XCdc">    -16.99049946 </i>
    <i name="pawpsdc">     70.78661021 </i>
    <i name="pawaedc">    -35.68611982 </i>
    <i name="eentropy">     -0.05641896 </i>
    <i name="bandstr">     36.20785165 </i>
    <i name="atom">    206.11247263 </i>
    <i name="e_fr_energy">    -12.11268634 </i>
    <i name="e_wo_entrp">    -12.05626739 </i>
    <i name="e_0_energy">    -12.08447687 </i>
   </energy>
  </scstep>
  <scstep>
   <time name="dav">    0.04    0.03</time>
   <time name="total">    0.07    0.08</time>
   <energy>
    <i name="e_fr_energy">    -11.84213853 </i>
    <i name="e_wo_entrp">    -11.78571957 </i>
    <i name="e_0_energy">    -11.81392905 </i>
   </energy>
  </scstep>
  <scstep>
   <time name="dav">    0.03    0.03</time>
   <time name="total">    0.06    0.07</time>
   <energy>
    <i name="e_fr_energy">    -11.70241799 </i>
    <i name="e_wo_entrp">    -11.64599903 </i>
    <i name="e_0_energy">    -11.67420851 </i>
   </energy>
  </scstep>
  <scstep>
   <time name="dav">    0.03    0.03</time>
   <time name="total">    0.06    0.07</time>
   <energy>
    <i name="e_fr_energy">    -11.70304476 </i>
    <i name="e_wo_entrp">    -11.64662580 </i>
    <i name="e_0_energy">    -11.67483528 </i>
   </energy>
  </scstep>
  <scstep>
   <time name="dav">    0.02    0.02</time>
   <time name="total">    0.04    0.05</time>
   <energy>
    <i name="alphaZ">      4.99425214 </i>
    <i name="ewald">   -275.22881378 </i>
    <i name="hartreedc">     -2.58063357 </i>
    <i name="XCdc">    -16.78845968 </i>
    <i name="pawpsdc">     76.92207592 </i>
    <i name="pawaedc">    -41.98055761 </i>
    <i name="eentropy">     -0.05641896 </i>
    <i name="bandstr">     36.90321594 </i>
    <i name="atom">    206.11247263 </i>
    <i name="e_fr_energy">    -11.70286697 </i>
    <i name="e_wo_entrp">    -11.64644801 </i>
    <i name="e_0_energy">    -11.67465749 </i>
   </energy>
  </scstep>
  <structure>
   <crystal>
    <varray name="basis" >
     <v>      -2.18343459       2.18343459       1.41384888 </v>
     <v>       2.18343459      -2.18343459       1.41384888 </v>
     <v>       2.18343459       2.18343459      -1.41384888 </v>
    </varray>
    <i name="volume">     26.96145684 </i>
    <varray name="rec_basis" >
     <v>       0.00000000       0.22899701       0.35364458 </v>
     <v>       0.22899701       0.00000000       0.35364458 </v>
     <v>       0.22899701       0.22899701      -0.00000000 </v>
    </varray>
   </crystal>
   <varray name="positions" >
    <v>       0.25000000       0.75000000       0.50000000 </v>
    <v>      -0.00000000      -0.00000000      -0.00000000 </v>
   </varray>
  </structure>
  <varray name="forces" >
   <v>       0.00000000      -0.00000000       0.00000000 </v>
   <v>      -0.00000000       0.00000000      -0.00000000 </v>
  </varray>
  <varray name="stress" >
   <v>     412.29330062      -0.00000000      -0.00000000 </v>
   <v>      -0.00000000     412.29330062       0.00000000 </v>
   <v>      -0.00000000       0.00000000    -234.43860762 </v>
  </varray>
  <energy>
   <i name="e_fr_energy">    -11.70286697 </i>
   <i name="e_wo_entrp">    -11.67465749 </i>
   <i name="e_0_energy">     -0.05641896 </i>
  </energy>
  <time name="totalsc">    0.42    0.51</time>
 </calculation>
 <calculation>
  <scstep>
   <time name="dav">    0.02    0.02</time>
   <time name="total">    0.06    0.06</time>
   <energy>
    <i name="alphaZ">      4.61512787 </i>
    <i name="ewald">   -269.41206712 </i>
    <i name="hartreedc">     -2.32423988 </i>
    <i name="XCdc">    -17.21616418 </i>
    <i name="pawpsdc">     76.83913194 </i>
    <i name="pawaedc">    -41.89678760 </i>
    <i name="eentropy">     -0.05641896 </i>
    <i name="bandstr">     30.90730022 </i>
    <i name="atom">    206.11247263 </i>
    <i name="e_fr_energy">    -12.43164508 </i>
    <i name="e_wo_entrp">    -12.37522612 </i>
    <i name="e_0_energy">    -12.40343560 </i>
   </energy>
  </scstep>
  <scstep>
   <time name="dav">    0.02    0.03</time>
   <time name="total">    0.06    0.07</time>
   <energy>
    <i name="e_fr_energy">    -12.34930730 </i>
    <i name="e_wo_entrp">    -12.29288834 </i>
    <i name="e_0_energy">    -12.32109782 </i>
   </energy>
  </scstep>
  <scstep>
   <time name="dav">    0.02    0.03</time>
   <time name="total">    0.06    0.07</time>
   <energy>
    <i name="e_fr_energy">    -12.30472118 </i>
    <i name="e_wo_entrp">    -12.24830222 </i>
    <i name="e_0_energy">    -12.27651170 </i>
   </energy>
  </scstep>
  <scstep>
   <time name="dav">    0.02    0.02</time>
   <time name="total">    0.05    0.06</time>
   <energy>
    <i name="alphaZ">      4.61512787 </i>
    <i name="ewald">   -269.41206712 </i>
    <i name="hartreedc">     -2.04310971 </i>
    <i name="XCdc">    -17.33004563 </i>
    <i name="pawpsdc">     72.29639905 </i>
    <i name="pawaedc">    -37.23697500 </i>
    <i name="eentropy">     -0.05641896 </i>
    <i name="bandstr">     30.74977105 </i>
    <i name="atom">    206.11247263 </i>
    <i name="e_fr_energy">    -12.30484582 </i>
    <i name="e_wo_entrp">    -12.24842686 </i>
    <i name="e_0_energy">    -12.27663634 </i>
   </energy>
  </scstep>
  <structure>
   <crystal>
    <varray name="basis" >
     <v>      -2.34064418       2.34064418       1.33137162 </v>
     <v>       2.34064418      -2.34064418       1.33137162 </v>
     <v>       2.34064418       2.34064418      -1.33137162 </v>
    </varray>
    <i name="volume">     29.17629098 </i>
    <varray name="rec_basis" >
     <v>      -0.00000000       0.21361641       0.37555254 </v>
     <v>       0.21361641      -0.00000000       0.37555254 </v>
     <v>       0.21361641       0.21361641      -0.00000000 </v>
    </varray>
   </crystal>
   <varray name="positions" >
    <v>       0.25000000       0.75000000       0.50000000 </v>
    <v>      -0.00000000      -0.00000000      -0.00000000 </v>
   </varray>
  </structure>
  <varray name="forces" >
   <v>      -0.00000000      -0.00000000       0.00000000 </v>
   <v>       0.00000000       0.00000000      -0.00000000 </v>
  </varray>
  <varray name="stress" >
   <v>     -22.71577669       0.00000000      -0.00000000 </v>
   <v>       0.00000000     -22.71577669       0.00000000 </v>
   <v>      -0.00000000       0.00000000     -20.83370159 </v>
  </varray>
  <energy>
   <i name="e_fr_energy">    -12.30484582 </i>
   <i name="e_wo_entrp">    -12.27663634 </i>
   <i name="e_0_energy">     -0.05641896 </i>
  </energy>
  <time name="totalsc">    0.35    0.44</time>
 </calculation>
 <calculation>
  <scstep>
   <time name="dav">    0.02    0.02</time>
   <time name="total">    0.06    0.06</time>
   <energy>
    <i name="alphaZ">      4.62326705 </i>
    <i name="ewald">   -269.55573921 </i>
    <i name="hartreedc">     -2.06162870 </i>
    <i name="XCdc">    -17.32371161 </i>
    <i name="pawpsdc">     72.13782223 </i>
    <i name="pawaedc">    -37.07289339 </i>
    <i name="eentropy">     -0.05641896 </i>
    <i name="bandstr">     30.89148861 </i>
    <i name="atom">    206.11247263 </i>
    <i name="e_fr_energy">    -12.30534135 </i>
    <i name="e_wo_entrp">    -12.24892239 </i>
    <i name="e_0_energy">    -12.27713187 </i>
   </energy>
  </scstep>
  <scstep>
   <time name="dav">    0.01    0.01</time>
   <time name="total">    0.04    0.05</time>
   <energy>
    <i name="alphaZ">      4.62326705 </i>
    <i name="ewald">   -269.55573921 </i>
    <i name="hartreedc">     -2.06057536 </i>
    <i name="XCdc">    -17.32288211 </i>
    <i name="pawpsdc">     72.17068186 </i>
    <i name="pawaedc">    -37.10652451 </i>
    <i name="eentropy">     -0.05641896 </i>
    <i name="bandstr">     30.89043978 </i>
    <i name="atom">    206.11247263 </i>
    <i name="e_fr_energy">    -12.30527883 </i>
    <i name="e_wo_entrp">    -12.24885987 </i>
    <i name="e_0_energy">    -12.27706935 </i>
   </energy>
  </scstep>
  <structure>
   <crystal>
    <varray name="basis" >
     <v>      -2.33682533       2.33682533       1.33337511 </v>
     <v>       2.33682533      -2.33682533       1.33337511 </v>
     <v>       2.33682533       2.33682533      -1.33337511 </v>
    </varray>
    <i name="volume">     29.12492660 </i>
    <varray name="rec_basis" >
     <v>      -0.00000000       0.21396550       0.37498825 </v>
     <v>       0.21396550      -0.00000000       0.37498825 </v>
     <v>       0.21396550       0.21396550       0.00000000 </v>
    </varray>
   </crystal>
   <varray name="positions" >
    <v>       0.25000000       0.75000000       0.50000000 </v>
    <v>      -0.00000000      -0.00000000      -0.00000000 </v>
   </varray>
  </structure>
  <varray name="forces" >
   <v>      -0.00000000       0.00000000       0.00000000 </v>
   <v>       0.00000000      -0.00000000      -0.00000000 </v>
  </varray>
  <varray name="stress" >
   <v>     -16.21679965       0.00000000       0.00000000 </v>
   <v>       0.00000000     -16.21679965      -0.00000000 </v>
   <v>       0.00000000      -0.00000000     -29.95524477 </v>
  </varray>
  <energy>
   <i name="e_fr_energy">    -12.30527883 </i>
   <i name="e_wo_entrp">    -12.27706935 </i>
   <i name="e_0_energy">     -0.05641896 </i>
  </energy>
  <time name="totalsc">    0.22    0.29</time>
 </calculation>
 <calculation>
  <scstep>
   <time name="dav">    0.01    0.01</time>
   <time name="total">    0.05    0.05</time>
   <energy>
    <i name="alphaZ">      4.62407714 </i>
    <i name="ewald">   -269.56997964 </i>
    <i name="hartreedc">     -2.05892306 </i>
    <i name="XCdc">    -17.32078155 </i>
    <i name="pawpsdc">     72.21769814 </i>
    <i name="pawaedc">    -37.15459900 </i>
    <i name="eentropy">     -0.05641896 </i>
    <i name="bandstr">     30.90120671 </i>
    <i name="atom">    206.11247263 </i>
    <i name="e_fr_energy">    -12.30524760 </i>
    <i name="e_wo_entrp">    -12.24882864 </i>
    <i name="e_0_energy">    -12.27703812 </i>
   </energy>
  </scstep>
  <scstep>
   <time name="dav">    0.01    0.01</time>
   <time name="total">    0.04    0.05</time>
   <energy>
    <i name="alphaZ">      4.62407714 </i>
    <i name="ewald">   -269.56997964 </i>
    <i name="hartreedc">     -2.05855827 </i>
    <i name="XCdc">    -17.32067818 </i>
    <i name="pawpsdc">     72.22191010 </i>
    <i name="pawaedc">    -37.15894965 </i>
    <i name="eentropy">     -0.05641896 </i>
    <i name="bandstr">     30.90087737 </i>
    <i name="atom">    206.11247263 </i>
    <i name="e_fr_energy">    -12.30524746 </i>
    <i name="e_wo_entrp">    -12.24882850 </i>
    <i name="e_0_energy">    -12.27703798 </i>
   </energy>
  </scstep>
  <structure>
   <crystal>
    <varray name="basis" >
     <v>      -2.33644651       2.33644651       1.33357385 </v>
     <v>       2.33644651      -2.33644651       1.33357385 </v>
     <v>       2.33644651       2.33644651      -1.33357385 </v>
    </varray>
    <i name="volume">     29.11982427 </i>
    <varray name="rec_basis" >
     <v>      -0.00000000       0.21400019       0.37493237 </v>
     <v>       0.21400019      -0.00000000       0.37493237 </v>
     <v>       0.21400019       0.21400019      -0.00000000 </v>
    </varray>
   </crystal>
   <varray name="positions" >
    <v>       0.25000000       0.75000000       0.50000000 </v>
    <v>      -0.00000000      -0.00000000      -0.00000000 </v>
   </varray>
  </structure>
  <varray name="forces" >
   <v>      -0.00000000       0.00000000       0.00000000 </v>
   <v>       0.00000000      -0.00000000      -0.00000000 </v>
  </varray>
  <varray name="stress" >
   <v>     -14.13263718       0.00000000      -0.00000000 </v>
   <v>       0.00000000     -14.13263718       0.00000000 </v>
   <v>      -0.00000000       0.00000000     -32.06123656 </v>
  </varray>
  <energy>
   <i name="e_fr_energy">    -12.30524746 </i>
   <i name="e_wo_entrp">    -12.27703798 </i>
   <i name="e_0_energy">     -0.05641896 </i>
  </energy>
  <time name="totalsc">    0.22    0.28</time>
 </calculation>
 <calculation>
  <scstep>
   <time name="dav">    0.02    0.01</time>
   <time name="total">    0.05    0.05</time>
   <energy>
    <i name="alphaZ">      4.62355171 </i>
    <i name="ewald">   -269.56074433 </i>
    <i name="hartreedc">     -2.05800586 </i>
    <i name="XCdc">    -17.32111810 </i>
    <i name="pawpsdc">     72.22846212 </i>
    <i name="pawaedc">    -37.16572079 </i>
    <i name="eentropy">     -0.05641896 </i>
    <i name="bandstr">     30.89227244 </i>
    <i name="atom">    206.11247263 </i>
    <i name="e_fr_energy">    -12.30524914 </i>
    <i name="e_wo_entrp">    -12.24883018 </i>
    <i name="e_0_energy">    -12.27703966 </i>
   </energy>
  </scstep>
  <scstep>
   <time name="dav">    0.02    0.01</time>
   <time name="total">    0.04    0.05</time>
   <energy>
    <i name="alphaZ">      4.62355171 </i>
    <i name="ewald">   -269.56074433 </i>
    <i name="hartreedc">     -2.05797038 </i>
    <i name="XCdc">    -17.32115455 </i>
    <i name="pawpsdc">     72.22686289 </i>
    <i name="pawaedc">    -37.16408161 </i>
    <i name="eentropy">     -0.05641896 </i>
    <i name="bandstr">     30.89223370 </i>
    <i name="atom">    206.11247263 </i>
    <i name="e_fr_energy">    -12.30524891 </i>
    <i name="e_wo_entrp">    -12.24882995 </i>
    <i name="e_0_energy">    -12.27703943 </i>
   </energy>
  </scstep>
  <structure>
   <crystal>
    <varray name="basis" >
     <v>      -2.33669219       2.33669219       1.33344496 </v>
     <v>       2.33669219      -2.33669219       1.33344496 </v>
     <v>       2.33669219       2.33669219      -1.33344496 </v>
    </varray>
    <i name="volume">     29.12313350 </i>
    <varray name="rec_basis" >
     <v>       0.00000000       0.21397769       0.37496861 </v>
     <v>       0.21397769       0.00000000       0.37496861 </v>
     <v>       0.21397769       0.21397769      -0.00000000 </v>
    </varray>
   </crystal>
   <varray name="positions" >
    <v>       0.25000000       0.75000000       0.50000000 </v>
    <v>      -0.00000000      -0.00000000      -0.00000000 </v>
   </varray>
  </structure>
  <varray name="forces" >
   <v>       0.00000000      -0.00000000      -0.00000000 </v>
   <v>      -0.00000000       0.00000000       0.00000000 </v>
  </varray>
  <varray name="stress" >
   <v>     -14.54871323      -0.00000000      -0.00000000 </v>
   <v>      -0.00000000     -14.54871323       0.00000000 </v>
   <v>      -0.00000000       0.00000000     -31.69137924 </v>
  </varray>
  <energy>
   <i name="e_fr_energy">    -12.30524891 </i>
   <i name="e_wo_entrp">    -12.27703943 </i>
   <i name="e_0_energy">     -0.05641896 </i>
  </energy>
  <time name="totalsc">    0.22    0.27</time>
 </calculation>
 <calculation>
  <scstep>
   <time name="dav">    0.01    0.01</time>
   <time name="total">    0.05    0.05</time>
   <energy>
    <i name="alphaZ">      4.62339078 </i>
    <i name="ewald">   -269.55791488 </i>
    <i name="hartreedc">     -2.05783971 </i>
    <i name="XCdc">    -17.32140536 </i>
    <i name="pawpsdc">     72.22452481 </i>
    <i name="pawaedc">    -37.16169804 </i>
    <i name="eentropy">     -0.05641896 </i>
    <i name="bandstr">     30.88964025 </i>
    <i name="atom">    206.11247263 </i>
    <i name="e_fr_energy">    -12.30524850 </i>
    <i name="e_wo_entrp">    -12.24882954 </i>
    <i name="e_0_energy">    -12.27703902 </i>
   </energy>
  </scstep>
  <scstep>
   <time name="dav">    0.01    0.01</time>
   <time name="total">    0.04    0.05</time>
   <energy>
    <i name="alphaZ">      4.62339078 </i>
    <i name="ewald">   -269.55791488 </i>
    <i name="hartreedc">     -2.05786374 </i>
    <i name="XCdc">    -17.32142071 </i>
    <i name="pawpsdc">     72.22395115 </i>
    <i name="pawaedc">    -37.16110965 </i>
    <i name="eentropy">     -0.05641896 </i>
    <i name="bandstr">     30.88966493 </i>
    <i name="atom">    206.11247263 </i>
    <i name="e_fr_energy">    -12.30524846 </i>
    <i name="e_wo_entrp">    -12.24882950 </i>
    <i name="e_0_energy">    -12.27703898 </i>
   </energy>
  </scstep>
  <structure>
   <crystal>
    <varray name="basis" >
     <v>      -2.33676746       2.33676746       1.33340547 </v>
     <v>       2.33676746      -2.33676746       1.33340547 </v>
     <v>       2.33676746       2.33676746      -1.33340547 </v>
    </varray>
    <i name="volume">     29.12414719 </i>
    <varray name="rec_basis" >
     <v>      -0.00000000       0.21397080       0.37497971 </v>
     <v>       0.21397080      -0.00000000       0.37497971 </v>
     <v>       0.21397080       0.21397080       0.00000000 </v>
    </varray>
   </crystal>
   <varray name="positions" >
    <v>       0.25000000       0.75000000       0.50000000 </v>
    <v>      -0.00000000      -0.00000000      -0.00000000 </v>
   </varray>
  </structure>
  <varray name="forces" >
   <v>       0.00000000       0.00000000      -0.00000000 </v>
   <v>      -0.00000000      -0.00000000       0.00000000 </v>
  </varray>
  <varray name="stress" >
   <v>     -14.75537376      -0.00000000      -0.00000000 </v>
   <v>      -0.00000000     -14.75537376       0.00000000 </v>
   <v>      -0.00000000       0.00000000     -31.45651204 </v>
  </varray>
  <energy>
   <i name="e_fr_energy">    -12.30524846 </i>
   <i name="e_wo_entrp">    -12.27703898 </i>
   <i name="e_0_energy">     -0.05641896 </i>
  </energy>
  <time name="totalsc">    0.22    0.29</time>
 </calculation>
 <calculation>
  <scstep>
   <time name="dav">    0.01    0.01</time>
   <time name="total">    0.05    0.05</time>
   <energy>
    <i name="alphaZ">      4.62332871 </i>
    <i name="ewald">   -269.55682351 </i>
    <i name="hartreedc">     -2.05787175 </i>
    <i name="XCdc">    -17.32151576 </i>
    <i name="pawpsdc">     72.22314065 </i>
    <i name="pawaedc">    -37.16028075 </i>
    <i name="eentropy">     -0.05641896 </i>
    <i name="bandstr">     30.88872049 </i>
    <i name="atom">    206.11247263 </i>
    <i name="e_fr_energy">    -12.30524825 </i>
    <i name="e_wo_entrp">    -12.24882929 </i>
    <i name="e_0_energy">    -12.27703877 </i>
   </energy>
  </scstep>
  <scstep>
   <time name="dav">    0.01    0.01</time>
   <time name="total">    0.04    0.05</time>
   <energy>
    <i name="alphaZ">      4.62332871 </i>
    <i name="ewald">   -269.55682351 </i>
    <i name="hartreedc">     -2.05787930 </i>
    <i name="XCdc">    -17.32152238 </i>
    <i name="pawpsdc">     72.22289170 </i>
    <i name="pawaedc">    -37.16002484 </i>
    <i name="eentropy">     -0.05641896 </i>
    <i name="bandstr">     30.88872771 </i>
    <i name="atom">    206.11247263 </i>
    <i name="e_fr_energy">    -12.30524824 </i>
    <i name="e_wo_entrp">    -12.24882928 </i>
    <i name="e_0_energy">    -12.27703876 </i>
   </energy>
  </scstep>
  <structure>
   <crystal>
    <varray name="basis" >
     <v>      -2.33679649       2.33679649       1.33339024 </v>
     <v>       2.33679649      -2.33679649       1.33339024 </v>
     <v>       2.33679649       2.33679649      -1.33339024 </v>
    </varray>
    <i name="volume">     29.12453817 </i>
    <varray name="rec_basis" >
     <v>      -0.00000000       0.21396814       0.37498400 </v>
     <v>       0.21396814      -0.00000000       0.37498400 </v>
     <v>       0.21396814       0.21396814       0.00000000 </v>
    </varray>
   </crystal>
   <varray name="positions" >
    <v>       0.25000000       0.75000000       0.50000000 </v>
    <v>      -0.00000000      -0.00000000      -0.00000000 </v>
   </varray>
  </structure>
  <varray name="forces" >
   <v>       0.00000000       0.00000000       0.00000000 </v>
   <v>      -0.00000000      -0.00000000      -0.00000000 </v>
  </varray>
  <varray name="stress" >
   <v>     -14.83493166      -0.00000000       0.00000000 </v>
   <v>      -0.00000000     -14.83493166      -0.00000000 </v>
   <v>       0.00000000      -0.00000000     -31.38212158 </v>
  </varray>
  <energy>
   <i name="e_fr_energy">    -12.30524824 </i>
   <i name="e_wo_entrp">    -12.27703876 </i>
   <i name="e_0_energy">     -0.05641896 </i>
  </energy>
  <time name="totalsc">    0.21    0.29</time>
 </calculation>
 <calculation>
  <scstep>
   <time name="dav">    0.01    0.01</time>
   <time name="total">    0.05    0.05</time>
   <energy>
    <i name="alphaZ">      4.62329950 </i>
    <i name="ewald">   -269.55630970 </i>
    <i name="hartreedc">     -2.05787992 </i>
    <i name="XCdc">    -17.32156534 </i>
    <i name="pawpsdc">     72.22255847 </i>
    <i name="pawaedc">    -37.15968291 </i>
    <i name="eentropy">     -0.05641896 </i>
    <i name="bandstr">     30.88827811 </i>
    <i name="atom">    206.11247263 </i>
    <i name="e_fr_energy">    -12.30524813 </i>
    <i name="e_wo_entrp">    -12.24882917 </i>
    <i name="e_0_energy">    -12.27703865 </i>
   </energy>
  </scstep>
  <scstep>
   <time name="dav">    0.01    0.01</time>
   <time name="total">    0.04    0.05</time>
   <energy>
    <i name="alphaZ">      4.62329950 </i>
    <i name="ewald">   -269.55630970 </i>
    <i name="hartreedc">     -2.05788273 </i>
    <i name="XCdc">    -17.32156839 </i>
    <i name="pawpsdc">     72.22244214 </i>
    <i name="pawaedc">    -37.15956325 </i>
    <i name="eentropy">     -0.05641896 </i>
    <i name="bandstr">     30.88828064 </i>
    <i name="atom">    206.11247263 </i>
    <i name="e_fr_energy">    -12.30524812 </i>
    <i name="e_wo_entrp">    -12.24882917 </i>
    <i name="e_0_energy">    -12.27703865 </i>
   </energy>
  </scstep>
  <structure>
   <crystal>
    <varray name="basis" >
     <v>      -2.33681016       2.33681016       1.33338307 </v>
     <v>       2.33681016      -2.33681016       1.33338307 </v>
     <v>       2.33681016       2.33681016      -1.33338307 </v>
    </varray>
    <i name="volume">     29.12472223 </i>
    <varray name="rec_basis" >
     <v>      -0.00000000       0.21396689       0.37498601 </v>
     <v>       0.21396689      -0.00000000       0.37498601 </v>
     <v>       0.21396689       0.21396689      -0.00000000 </v>
    </varray>
   </crystal>
   <varray name="positions" >
    <v>       0.25000000       0.75000000       0.50000000 </v>
    <v>      -0.00000000      -0.00000000      -0.00000000 </v>
   </varray>
  </structure>
  <varray name="forces" >
   <v>       0.00000000      -0.00000000      -0.00000000 </v>
   <v>      -0.00000000       0.00000000       0.00000000 </v>
  </varray>
  <varray name="stress" >
   <v>     -14.87075391      -0.00000000       0.00000000 </v>
   <v>      -0.00000000     -14.87075391      -0.00000000 </v>
   <v>       0.00000000      -0.00000000     -31.34920310 </v>
  </varray>
  <energy>
   <i name="e_fr_energy">    -12.30524812 </i>
   <i name="e_wo_entrp">    -12.27703865 </i>
   <i name="e_0_energy">     -0.05641896 </i>
  </energy>
  <time name="totalsc">    0.22    0.30</time>
 </calculation>
 <calculation>
  <scstep>
   <time name="dav">    0.01    0.01</time>
   <time name="total">    0.05    0.05</time>
   <energy>
    <i name="alphaZ">      4.62328327 </i>
    <i name="ewald">   -269.55602445 </i>
    <i name="hartreedc">     -2.05788191 </i>
    <i name="XCdc">    -17.32159122 </i>
    <i name="pawpsdc">     72.22228884 </i>
    <i name="pawaedc">    -37.15940584 </i>
    <i name="eentropy">     -0.05641896 </i>
    <i name="bandstr">     30.88802959 </i>
    <i name="atom">    206.11247263 </i>
    <i name="e_fr_energy">    -12.30524806 </i>
    <i name="e_wo_entrp">    -12.24882910 </i>
    <i name="e_0_energy">    -12.27703858 </i>
   </energy>
  </scstep>
  <scstep>
   <time name="dav">    0.01    0.01</time>
   <time name="total">    0.04    0.05</time>
   <energy>
    <i name="alphaZ">      4.62328327 </i>
    <i name="ewald">   -269.55602445 </i>
    <i name="hartreedc">     -2.05788316 </i>
    <i name="XCdc">    -17.32159286 </i>
    <i name="pawpsdc">     72.22222542 </i>
    <i name="pawaedc">    -37.15934062 </i>
    <i name="eentropy">     -0.05641896 </i>
    <i name="bandstr">     30.88803066 </i>
    <i name="atom">    206.11247263 </i>
    <i name="e_fr_energy">    -12.30524806 </i>
    <i name="e_wo_entrp">    -12.24882910 </i>
    <i name="e_0_energy">    -12.27703858 </i>
   </energy>
  </scstep>
  <structure>
   <crystal>
    <varray name="basis" >
     <v>      -2.33681775       2.33681775       1.33337909 </v>
     <v>       2.33681775      -2.33681775       1.33337909 </v>
     <v>       2.33681775       2.33681775      -1.33337909 </v>
    </varray>
    <i name="volume">     29.12482442 </i>
    <varray name="rec_basis" >
     <v>      -0.00000000       0.21396619       0.37498713 </v>
     <v>       0.21396619      -0.00000000       0.37498713 </v>
     <v>       0.21396619       0.21396619       0.00000000 </v>
    </varray>
   </crystal>
   <varray name="positions" >
    <v>       0.25000000       0.75000000       0.50000000 </v>
    <v>      -0.00000000      -0.00000000      -0.00000000 </v>
   </varray>
  </structure>
  <varray name="forces" >
   <v>       0.00000000      -0.00000000      -0.00000000 </v>
   <v>      -0.00000000       0.00000000       0.00000000 </v>
  </varray>
  <varray name="stress" >
   <v>     -14.89000322      -0.00000000      -0.00000000 </v>
   <v>      -0.00000000     -14.89000322      -0.00000000 </v>
   <v>      -0.00000000      -0.00000000     -31.33162523 </v>
  </varray>
  <energy>
   <i name="e_fr_energy">    -12.30524806 </i>
   <i name="e_wo_entrp">    -12.27703858 </i>
   <i name="e_0_energy">     -0.05641896 </i>
  </energy>
  <time name="totalsc">    0.22    0.28</time>
 </calculation>
 <calculation>
  <scstep>
   <time name="dav">    0.01    0.01</time>
   <time name="total">    0.05    0.05</time>
   <energy>
    <i name="alphaZ">      4.62327516 </i>
    <i name="ewald">   -269.55588183 </i>
    <i name="hartreedc">     -2.05788263 </i>
    <i name="XCdc">    -17.32160446 </i>
    <i name="pawpsdc">     72.22214214 </i>
    <i name="pawaedc">    -37.15925512 </i>
    <i name="eentropy">     -0.05641896 </i>
    <i name="bandstr">     30.88790504 </i>
    <i name="atom">    206.11247263 </i>
    <i name="e_fr_energy">    -12.30524803 </i>
    <i name="e_wo_entrp">    -12.24882907 </i>
    <i name="e_0_energy">    -12.27703855 </i>
   </energy>
  </scstep>
  <scstep>
   <time name="dav">    0.01    0.01</time>
   <time name="total">    0.04    0.05</time>
   <energy>
    <i name="alphaZ">      4.62327516 </i>
    <i name="ewald">   -269.55588183 </i>
    <i name="hartreedc">     -2.05788335 </i>
    <i name="XCdc">    -17.32160526 </i>
    <i name="pawpsdc">     72.22211056 </i>
    <i name="pawaedc">    -37.15922264 </i>
    <i name="eentropy">     -0.05641896 </i>
    <i name="bandstr">     30.88790566 </i>
    <i name="atom">    206.11247263 </i>
    <i name="e_fr_energy">    -12.30524803 </i>
    <i name="e_wo_entrp">    -12.24882907 </i>
    <i name="e_0_energy">    -12.27703855 </i>
   </energy>
  </scstep>
  <structure>
   <crystal>
    <varray name="basis" >
     <v>      -2.33682154       2.33682154       1.33337710 </v>
     <v>       2.33682154      -2.33682154       1.33337710 </v>
     <v>       2.33682154       2.33682154      -1.33337710 </v>
    </varray>
    <i name="volume">     29.12487551 </i>
    <varray name="rec_basis" >
     <v>      -0.00000000       0.21396585       0.37498769 </v>
     <v>       0.21396585      -0.00000000       0.37498769 </v>
     <v>       0.21396585       0.21396585      -0.00000000 </v>
    </varray>
   </crystal>
   <varray name="positions" >
    <v>       0.25000000       0.75000000       0.50000000 </v>
    <v>      -0.00000000      -0.00000000      -0.00000000 </v>
   </varray>
  </structure>
  <varray name="forces" >
   <v>      -0.00000000       0.00000000      -0.00000000 </v>
   <v>       0.00000000      -0.00000000       0.00000000 </v>
  </varray>
  <varray name="stress" >
   <v>     -14.89987030      -0.00000000      -0.00000000 </v>
   <v>      -0.00000000     -14.89987030      -0.00000000 </v>
   <v>      -0.00000000      -0.00000000     -31.32245086 </v>
  </varray>
  <energy>
   <i name="e_fr_energy">    -12.30524803 </i>
   <i name="e_wo_entrp">    -12.27703855 </i>
   <i name="e_0_energy">     -0.05641896 </i>
  </energy>
  <time name="totalsc">    0.66    0.91</time>
 </calculation>
 <calculation>
  <scstep>
   <time name="dav">    0.01    0.01</time>
   <time name="total">    0.05    0.05</time>
   <energy>
    <i name="alphaZ">      4.62327111 </i>
    <i name="ewald">   -269.55581052 </i>
    <i name="hartreedc">     -2.05788304 </i>
    <i name="XCdc">    -17.32161106 </i>
    <i name="pawpsdc">     72.22206913 </i>
    <i name="pawaedc">    -37.15918010 </i>
    <i name="eentropy">     -0.05641896 </i>
    <i name="bandstr">     30.88784281 </i>
    <i name="atom">    206.11247263 </i>
    <i name="e_fr_energy">    -12.30524801 </i>
    <i name="e_wo_entrp">    -12.24882905 </i>
    <i name="e_0_energy">    -12.27703853 </i>
   </energy>
  </scstep>
  <scstep>
   <time name="dav">    0.01    0.01</time>
   <time name="total">    0.04    0.05</time>
   <energy>
    <i name="alphaZ">      4.62327111 </i>
    <i name="ewald">   -269.55581052 </i>
    <i name="hartreedc">     -2.05788342 </i>
    <i name="XCdc">    -17.32161147 </i>
    <i name="pawpsdc">     72.22205333 </i>
    <i name="pawaedc">    -37.15916385 </i>
    <i name="eentropy">     -0.05641896 </i>
    <i name="bandstr">     30.88784315 </i>
    <i name="atom">    206.11247263 </i>
    <i name="e_fr_energy">    -12.30524801 </i>
    <i name="e_wo_entrp">    -12.24882905 </i>
    <i name="e_0_energy">    -12.27703853 </i>
   </energy>
  </scstep>
  <structure>
   <crystal>
    <varray name="basis" >
     <v>      -2.33682344       2.33682344       1.33337611 </v>
     <v>       2.33682344      -2.33682344       1.33337611 </v>
     <v>       2.33682344       2.33682344      -1.33337611 </v>
    </varray>
    <i name="volume">     29.12490105 </i>
    <varray name="rec_basis" >
     <v>       0.00000000       0.21396567       0.37498797 </v>
     <v>       0.21396567       0.00000000       0.37498797 </v>
     <v>       0.21396567       0.21396567      -0.00000000 </v>
    </varray>
   </crystal>
   <varray name="positions" >
    <v>       0.25000000       0.75000000       0.50000000 </v>
    <v>      -0.00000000      -0.00000000      -0.00000000 </v>
   </varray>
  </structure>
  <varray name="forces" >
   <v>       0.00000000       0.00000000      -0.00000000 </v>
   <v>      -0.00000000      -0.00000000       0.00000000 </v>
  </varray>
  <varray name="stress" >
   <v>     -14.90473683      -0.00000000      -0.00000000 </v>
   <v>      -0.00000000     -14.90473683      -0.00000000 </v>
   <v>      -0.00000000      -0.00000000     -31.31791685 </v>
  </varray>
  <energy>
   <i name="e_fr_energy">    -12.30524801 </i>
   <i name="e_wo_entrp">    -12.27703853 </i>
   <i name="e_0_energy">     -0.05641896 </i>
  </energy>
  <time name="totalsc">    0.22    0.28</time>
 </calculation>
 <calculation>
  <scstep>
   <time name="dav">    0.01    0.01</time>
   <time name="total">    0.05    0.05</time>
   <energy>
    <i name="alphaZ">      4.62326908 </i>
    <i name="ewald">   -269.55577486 </i>
    <i name="hartreedc">     -2.05788329 </i>
    <i name="XCdc">    -17.32161438 </i>
    <i name="pawpsdc">     72.22203265 </i>
    <i name="pawaedc">    -37.15914263 </i>
    <i name="eentropy">     -0.05641896 </i>
    <i name="bandstr">     30.88781177 </i>
    <i name="atom">    206.11247263 </i>
    <i name="e_fr_energy">    -12.30524800 </i>
    <i name="e_wo_entrp">    -12.24882904 </i>
    <i name="e_0_energy">    -12.27703852 </i>
   </energy>
  </scstep>
  <scstep>
   <time name="dav">    0.01    0.01</time>
   <time name="total">    0.04    0.05</time>
   <energy>
    <i name="alphaZ">      4.62326908 </i>
    <i name="ewald">   -269.55577486 </i>
    <i name="hartreedc">     -2.05788348 </i>
    <i name="XCdc">    -17.32161458 </i>
    <i name="pawpsdc">     72.22202470 </i>
    <i name="pawaedc">    -37.15913445 </i>
    <i name="eentropy">     -0.05641896 </i>
    <i name="bandstr">     30.88781194 </i>
    <i name="atom">    206.11247263 </i>
    <i name="e_fr_energy">    -12.30524800 </i>
    <i name="e_wo_entrp">    -12.24882904 </i>
    <i name="e_0_energy">    -12.27703852 </i>
   </energy>
  </scstep>
  <structure>
   <crystal>
    <varray name="basis" >
     <v>      -2.33682438       2.33682438       1.33337561 </v>
     <v>       2.33682438      -2.33682438       1.33337561 </v>
     <v>       2.33682438       2.33682438      -1.33337561 </v>
    </varray>
    <i name="volume">     29.12491383 </i>
    <varray name="rec_basis" >
     <v>       0.00000000       0.21396559       0.37498811 </v>
     <v>       0.21396559       0.00000000       0.37498811 </v>
     <v>       0.21396559       0.21396559      -0.00000000 </v>
    </varray>
   </crystal>
   <varray name="positions" >
    <v>       0.25000000       0.75000000       0.50000000 </v>
    <v>      -0.00000000      -0.00000000      -0.00000000 </v>
   </varray>
  </structure>
  <varray name="forces" >
   <v>      -0.00000000       0.00000000       0.00000000 </v>
   <v>       0.00000000      -0.00000000      -0.00000000 </v>
  </varray>
  <varray name="stress" >
   <v>     -14.90717766      -0.00000000       0.00000000 </v>
   <v>      -0.00000000     -14.90717766      -0.00000000 </v>
   <v>       0.00000000      -0.00000000     -31.31565531 </v>
  </varray>
  <energy>
   <i name="e_fr_energy">    -12.30524800 </i>
   <i name="e_wo_entrp">    -12.27703852 </i>
   <i name="e_0_energy">     -0.05641896 </i>
  </energy>
  <time name="totalsc">    0.22    0.29</time>
 </calculation>
 <calculation>
  <scstep>
   <time name="dav">    0.01    0.01</time>
   <time name="total">    0.05    0.05</time>
   <energy>
    <i name="alphaZ">      4.62326807 </i>
    <i name="ewald">   -269.55575704 </i>
    <i name="hartreedc">     -2.05788342 </i>
    <i name="XCdc">    -17.32161604 </i>
    <i name="pawpsdc">     72.22201434 </i>
    <i name="pawaedc">    -37.15912382 </i>
    <i name="eentropy">     -0.05641896 </i>
    <i name="bandstr">     30.88779624 </i>
    <i name="atom">    206.11247263 </i>
    <i name="e_fr_energy">    -12.30524799 </i>
    <i name="e_wo_entrp">    -12.24882904 </i>
    <i name="e_0_energy">    -12.27703852 </i>
   </energy>
  </scstep>
  <scstep>
   <time name="dav">    0.02    0.01</time>
   <time name="total">    0.04    0.05</time>
   <energy>
    <i name="alphaZ">      4.62326807 </i>
    <i name="ewald">   -269.55575704 </i>
    <i name="hartreedc">     -2.05788352 </i>
    <i name="XCdc">    -17.32161614 </i>
    <i name="pawpsdc">     72.22201036 </i>
    <i name="pawaedc">    -37.15911972 </i>
    <i name="eentropy">     -0.05641896 </i>
    <i name="bandstr">     30.88779633 </i>
    <i name="atom">    206.11247263 </i>
    <i name="e_fr_energy">    -12.30524799 </i>
    <i name="e_wo_entrp">    -12.24882904 </i>
    <i name="e_0_energy">    -12.27703851 </i>
   </energy>
  </scstep>
  <structure>
   <crystal>
    <varray name="basis" >
     <v>      -2.33682486       2.33682486       1.33337536 </v>
     <v>       2.33682486      -2.33682486       1.33337536 </v>
     <v>       2.33682486       2.33682486      -1.33337536 </v>
    </varray>
    <i name="volume">     29.12492021 </i>
    <varray name="rec_basis" >
     <v>      -0.00000000       0.21396554       0.37498818 </v>
     <v>       0.21396554      -0.00000000       0.37498818 </v>
     <v>       0.21396554       0.21396554      -0.00000000 </v>
    </varray>
   </crystal>
   <varray name="positions" >
    <v>       0.25000000       0.75000000       0.50000000 </v>
    <v>      -0.00000000      -0.00000000      -0.00000000 </v>
   </varray>
  </structure>
  <varray name="forces" >
   <v>      -0.00000000       0.00000000       0.00000000 </v>
   <v>       0.00000000      -0.00000000      -0.00000000 </v>
  </varray>
  <varray name="stress" >
   <v>     -14.90839826      -0.00000000      -0.00000000 </v>
   <v>      -0.00000000     -14.90839826       0.00000000 </v>
   <v>      -0.00000000       0.00000000     -31.31452063 </v>
  </varray>
  <energy>
   <i name="e_fr_energy">    -12.30524799 </i>
   <i name="e_wo_entrp">    -12.27703851 </i>
   <i name="e_0_energy">     -0.05641896 </i>
  </energy>
  <time name="totalsc">    0.22    0.28</time>
 </calculation>
 <calculation>
  <scstep>
   <time name="dav">    0.02    0.01</time>
   <time name="total">    0.05    0.05</time>
   <energy>
    <i name="alphaZ">      4.62326756 </i>
    <i name="ewald">   -269.55574812 </i>
    <i name="hartreedc">     -2.05788350 </i>
    <i name="XCdc">    -17.32161686 </i>
    <i name="pawpsdc">     72.22200519 </i>
    <i name="pawaedc">    -37.15911442 </i>
    <i name="eentropy">     -0.05641896 </i>
    <i name="bandstr">     30.88778849 </i>
    <i name="atom">    206.11247263 </i>
    <i name="e_fr_energy">    -12.30524799 </i>
    <i name="e_wo_entrp">    -12.24882903 </i>
    <i name="e_0_energy">    -12.27703851 </i>
   </energy>
  </scstep>
  <scstep>
   <time name="dav">    0.02    0.01</time>
   <time name="total">    0.04    0.05</time>
   <energy>
    <i name="alphaZ">      4.62326756 </i>
    <i name="ewald">   -269.55574812 </i>
    <i name="hartreedc">     -2.05788355 </i>
    <i name="XCdc">    -17.32161692 </i>
    <i name="pawpsdc">     72.22200320 </i>
    <i name="pawaedc">    -37.15911236 </i>
    <i name="eentropy">     -0.05641896 </i>
    <i name="bandstr">     30.88778853 </i>
    <i name="atom">    206.11247263 </i>
    <i name="e_fr_energy">    -12.30524799 </i>
    <i name="e_wo_entrp">    -12.24882903 </i>
    <i name="e_0_energy">    -12.27703851 </i>
   </energy>
  </scstep>
  <structure>
   <crystal>
    <varray name="basis" >
     <v>      -2.33682510       2.33682510       1.33337523 </v>
     <v>       2.33682510      -2.33682510       1.33337523 </v>
     <v>       2.33682510       2.33682510      -1.33337523 </v>
    </varray>
    <i name="volume">     29.12492341 </i>
    <varray name="rec_basis" >
     <v>      -0.00000000       0.21396552       0.37498822 </v>
     <v>       0.21396552      -0.00000000       0.37498822 </v>
     <v>       0.21396552       0.21396552       0.00000000 </v>
    </varray>
   </crystal>
   <varray name="positions" >
    <v>       0.25000000       0.75000000       0.50000000 </v>
    <v>      -0.00000000      -0.00000000      -0.00000000 </v>
   </varray>
  </structure>
  <varray name="forces" >
   <v>      -0.00000000       0.00000000      -0.00000000 </v>
   <v>       0.00000000      -0.00000000       0.00000000 </v>
  </varray>
  <varray name="stress" >
   <v>     -14.90900881       0.00000000       0.00000000 </v>
   <v>       0.00000000     -14.90900881      -0.00000000 </v>
   <v>       0.00000000      -0.00000000     -31.31395372 </v>
  </varray>
  <energy>
   <i name="e_fr_energy">    -12.30524799 </i>
   <i name="e_wo_entrp">    -12.27703851 </i>
   <i name="e_0_energy">     -0.05641896 </i>
  </energy>
  <time name="totalsc">    0.22    0.34</time>
  <eigenvalues>
   <array>
    <dimension dim="1">band</dimension>
    <dimension dim="2">kpoint</dimension>
    <dimension dim="3">spin</dimension>
    <field>eigene</field>
    <field>occ</field>
    <set>
     <set comment="spin 1">
      <set comment="kpoint 1">
       <r>    3.1954    1.0000 </r>
       <r>    3.1954    1.0000 </r>
       <r>    4.3565    1.0000 </r>
       <r>    4.3565    1.0000 </r>
       <r>   14.0772    0.0000 </r>
       <r>   14.0772    0.0000 </r>
       <r>   16.1707    0.0000 </r>
       <r>   16.1707    0.0000 </r>
      </set>
      <set comment="kpoint 2">
       <r>   -2.7884    1.0000 </r>
       <r>    3.0928    1.0000 </r>
       <r>    4.2057    1.0000 </r>
       <r>    9.8307    0.5000 </r>
       <r>   14.5879    0.0000 </r>
       <r>   16.3704    0.0000 </r>
       <r>   17.4444    0.0000 </r>
       <r>   17.5232    0.0000 </r>
      </set>
      <set comment="kpoint 3">
       <r>    0.5294    1.0000 </r>
       <r>    6.3767    1.0000 </r>
       <r>    6.5385    1.0000 </r>
       <r>    7.1882    1.0000 </r>
       <r>    7.1882    1.0000 </r>
       <r>   13.0302    0.0000 </r>
       <r>   13.0302    0.0000 </r>
       <r>   13.1725    0.0000 </r>
      </set>
     </set>
    </set>
   </array>
  </eigenvalues>
  <separator name="orbital magnetization" >
   <v name="MAGDIPOLOUT">      0.00000000      0.00000000      0.00000000</v>
  </separator>
  <dos>
   <i name="efermi">      9.83074222 </i>
   <total>
    <array>
     <dimension dim="1">gridpoints</dimension>
     <dimension dim="2">spin</dimension>
     <field>energy</field>
     <field>total</field>
     <field>integrated</field>
     <set>
      <set comment="spin 1">
       <r>    -4.7884     0.0000     0.0000 </r>
       <r>    -4.7074     0.0000     0.0000 </r>
       <r>    -4.6263     0.0000     0.0000 </r>
       <r>    -4.5453     0.0000     0.0000 </r>
       <r>    -4.4642     0.0000     0.0000 </r>
       <r>    -4.3832     0.0000     0.0000 </r>
       <r>    -4.3022     0.0000     0.0000 </r>
       <r>    -4.2211     0.0000     0.0000 </r>
       <r>    -4.1401     0.0000     0.0000 </r>
       <r>    -4.0591     0.0000     0.0000 </r>
       <r>    -3.9780     0.0000     0.0000 </r>
       <r>    -3.8970     0.0000     0.0000 </r>
       <r>    -3.8159     0.0000     0.0000 </r>
       <r>    -3.7349     0.0000     0.0000 </r>
       <r>    -3.6539     0.0000     0.0000 </r>
       <r>    -3.5728     0.0000     0.0000 </r>
       <r>    -3.4918     0.0000     0.0000 </r>
       <r>    -3.4107     0.0001     0.0000 </r>
       <r>    -3.3297     0.0007     0.0001 </r>
       <r>    -3.2487     0.0062     0.0006 </r>
       <r>    -3.1676     0.0382     0.0037 </r>
       <r>    -3.0866     0.1707     0.0175 </r>
       <r>    -3.0056     0.5533     0.0623 </r>
       <r>    -2.9245     1.3028     0.1679 </r>
       <r>    -2.8435     2.2282     0.3485 </r>
       <r>    -2.7624     2.7685     0.5728 </r>
       <r>    -2.6814     2.4991     0.7754 </r>
       <r>    -2.6004     1.6390     0.9082 </r>
       <r>    -2.5193     0.7808     0.9715 </r>
       <r>    -2.4383     0.2701     0.9934 </r>
       <r>    -2.3572     0.0679     0.9989 </r>
       <r>    -2.2762     0.0124     0.9999 </r>
       <r>    -2.1952     0.0016     1.0000 </r>
       <r>    -2.1141     0.0002     1.0000 </r>
       <r>    -2.0331     0.0000     1.0000 </r>
       <r>    -1.9520     0.0000     1.0000 </r>
       <r>    -1.8710     0.0000     1.0000 </r>
       <r>    -1.7900     0.0000     1.0000 </r>
       <r>    -1.7089     0.0000     1.0000 </r>
       <r>    -1.6279     0.0000     1.0000 </r>
       <r>    -1.5469     0.0000     1.0000 </r>
       <r>    -1.4658     0.0000     1.0000 </r>
       <r>    -1.3848     0.0000     1.0000 </r>
       <r>    -1.3037     0.0000     1.0000 </r>
       <r>    -1.2227     0.0000     1.0000 </r>
       <r>    -1.1417     0.0000     1.0000 </r>
       <r>    -1.0606     0.0000     1.0000 </r>
       <r>    -0.9796     0.0000     1.0000 </r>
       <r>    -0.8985     0.0000     1.0000 </r>
       <r>    -0.8175     0.0000     1.0000 </r>
       <r>    -0.7365     0.0000     1.0000 </r>
       <r>    -0.6554     0.0000     1.0000 </r>
       <r>    -0.5744     0.0000     1.0000 </r>
       <r>    -0.4934     0.0000     1.0000 </r>
       <r>    -0.4123     0.0000     1.0000 </r>
       <r>    -0.3313     0.0000     1.0000 </r>
       <r>    -0.2502     0.0000     1.0000 </r>
       <r>    -0.1692     0.0000     1.0000 </r>
       <r>    -0.0882     0.0000     1.0000 </r>
       <r>    -0.0071     0.0004     1.0000 </r>
       <r>     0.0739     0.0035     1.0003 </r>
       <r>     0.1550     0.0211     1.0020 </r>
       <r>     0.2360     0.0923     1.0095 </r>
       <r>     0.3170     0.2936     1.0333 </r>
       <r>     0.3981     0.6784     1.0883 </r>
       <r>     0.4791     1.1385     1.1805 </r>
       <r>     0.5601     1.3882     1.2930 </r>
       <r>     0.6412     1.2297     1.3927 </r>
       <r>     0.7222     0.7914     1.4568 </r>
       <r>     0.8033     0.3700     1.4868 </r>
       <r>     0.8843     0.1256     1.4970 </r>
       <r>     0.9653     0.0310     1.4995 </r>
       <r>     1.0464     0.0055     1.4999 </r>
       <r>     1.1274     0.0007     1.5000 </r>
       <r>     1.2085     0.0001     1.5000 </r>
       <r>     1.2895     0.0000     1.5000 </r>
       <r>     1.3705     0.0000     1.5000 </r>
       <r>     1.4516     0.0000     1.5000 </r>
       <r>     1.5326     0.0000     1.5000 </r>
       <r>     1.6137     0.0000     1.5000 </r>
       <r>     1.6947     0.0000     1.5000 </r>
       <r>     1.7757     0.0000     1.5000 </r>
       <r>     1.8568     0.0000     1.5000 </r>
       <r>     1.9378     0.0000     1.5000 </r>
       <r>     2.0188     0.0000     1.5000 </r>
       <r>     2.0999     0.0000     1.5000 </r>
       <r>     2.1809     0.0000     1.5000 </r>
       <r>     2.2620     0.0000     1.5000 </r>
       <r>     2.3430     0.0000     1.5000 </r>
       <r>     2.4240     0.0000     1.5000 </r>
       <r>     2.5051     0.0002     1.5000 </r>
       <r>     2.5861     0.0020     1.5002 </r>
       <r>     2.6672     0.0151     1.5014 </r>
       <r>     2.7482     0.0839     1.5082 </r>
       <r>     2.8292     0.3433     1.5360 </r>
       <r>     2.9103     1.0409     1.6204 </r>
       <r>     2.9913     2.3538     1.8111 </r>
       <r>     3.0723     3.9946     2.1348 </r>
       <r>     3.1534     5.1139     2.5493 </r>
       <r>     3.2344     4.9524     2.9506 </r>
       <r>     3.3155     3.6265     3.2445 </r>
       <r>     3.3965     2.0013     3.4067 </r>
       <r>     3.4775     0.8277     3.4737 </r>
       <r>     3.5586     0.2549     3.4944 </r>
       <r>     3.6396     0.0584     3.4991 </r>
       <r>     3.7207     0.0131     3.5002 </r>
       <r>     3.8017     0.0244     3.5022 </r>
       <r>     3.8827     0.1163     3.5116 </r>
       <r>     3.9638     0.4285     3.5463 </r>
       <r>     4.0448     1.1735     3.6414 </r>
       <r>     4.1259     2.4215     3.8377 </r>
       <r>     4.2069     3.8351     4.1485 </r>
       <r>     4.2879     4.7507     4.5334 </r>
       <r>     4.3690     4.6587     4.9110 </r>
       <r>     4.4500     3.6122     5.2037 </r>
       <r>     4.5310     2.1843     5.3807 </r>
       <r>     4.6121     1.0104     5.4626 </r>
       <r>     4.6931     0.3512     5.4911 </r>
       <r>     4.7742     0.0905     5.4984 </r>
       <r>     4.8552     0.0171     5.4998 </r>
       <r>     4.9362     0.0024     5.5000 </r>
       <r>     5.0173     0.0002     5.5000 </r>
       <r>     5.0983     0.0000     5.5000 </r>
       <r>     5.1794     0.0000     5.5000 </r>
       <r>     5.2604     0.0000     5.5000 </r>
       <r>     5.3414     0.0000     5.5000 </r>
       <r>     5.4225     0.0000     5.5000 </r>
       <r>     5.5035     0.0000     5.5000 </r>
       <r>     5.5845     0.0000     5.5000 </r>
       <r>     5.6656     0.0000     5.5000 </r>
       <r>     5.7466     0.0000     5.5000 </r>
       <r>     5.8277     0.0003     5.5000 </r>
       <r>     5.9087     0.0026     5.5002 </r>
       <r>     5.9897     0.0166     5.5016 </r>
       <r>     6.0708     0.0776     5.5079 </r>
       <r>     6.1518     0.2671     5.5295 </r>
       <r>     6.2329     0.6840     5.5849 </r>
       <r>     6.3139     1.3249     5.6923 </r>
       <r>     6.3949     1.9850     5.8532 </r>
       <r>     6.4760     2.3541     6.0439 </r>
       <r>     6.5570     2.2402     6.2255 </r>
       <r>     6.6380     1.7037     6.3636 </r>
       <r>     6.7191     1.0198     6.4462 </r>
       <r>     6.8001     0.4945     6.4863 </r>
       <r>     6.8812     0.3054     6.5110 </r>
       <r>     6.9622     0.5341     6.5543 </r>
       <r>     7.0432     1.2122     6.6525 </r>
       <r>     7.1243     2.1350     6.8255 </r>
       <r>     7.2053     2.7460     7.0481 </r>
       <r>     7.2864     2.5670     7.2561 </r>
       <r>     7.3674     1.7435     7.3974 </r>
       <r>     7.4484     0.8602     7.4671 </r>
       <r>     7.5295     0.3082     7.4921 </r>
       <r>     7.6105     0.0802     7.4986 </r>
       <r>     7.6916     0.0151     7.4998 </r>
       <r>     7.7726     0.0021     7.5000 </r>
       <r>     7.8536     0.0002     7.5000 </r>
       <r>     7.9347     0.0000     7.5000 </r>
       <r>     8.0157     0.0000     7.5000 </r>
       <r>     8.0967     0.0000     7.5000 </r>
       <r>     8.1778     0.0000     7.5000 </r>
       <r>     8.2588     0.0000     7.5000 </r>
       <r>     8.3399     0.0000     7.5000 </r>
       <r>     8.4209     0.0000     7.5000 </r>
       <r>     8.5019     0.0000     7.5000 </r>
       <r>     8.5830     0.0000     7.5000 </r>
       <r>     8.6640     0.0000     7.5000 </r>
       <r>     8.7451     0.0000     7.5000 </r>
       <r>     8.8261     0.0000     7.5000 </r>
       <r>     8.9071     0.0000     7.5000 </r>
       <r>     8.9882     0.0000     7.5000 </r>
       <r>     9.0692     0.0000     7.5000 </r>
       <r>     9.1502     0.0000     7.5000 </r>
       <r>     9.2313     0.0001     7.5000 </r>
       <r>     9.3123     0.0014     7.5001 </r>
       <r>     9.3934     0.0107     7.5010 </r>
       <r>     9.4744     0.0602     7.5059 </r>
       <r>     9.5554     0.2457     7.5258 </r>
       <r>     9.6365     0.7279     7.5848 </r>
       <r>     9.7175     1.5659     7.7117 </r>
       <r>     9.7986     2.4471     7.9100 </r>
       <r>     9.8796     2.7781     8.1351 </r>
       <r>     9.9606     2.2914     8.3208 </r>
       <r>    10.0417     1.3731     8.4321 </r>
       <r>    10.1227     0.5976     8.4805 </r>
       <r>    10.2038     0.1889     8.4958 </r>
       <r>    10.2848     0.0433     8.4993 </r>
       <r>    10.3658     0.0072     8.4999 </r>
       <r>    10.4469     0.0009     8.5000 </r>
       <r>    10.5279     0.0001     8.5000 </r>
       <r>    10.6089     0.0000     8.5000 </r>
       <r>    10.6900     0.0000     8.5000 </r>
       <r>    10.7710     0.0000     8.5000 </r>
       <r>    10.8521     0.0000     8.5000 </r>
       <r>    10.9331     0.0000     8.5000 </r>
       <r>    11.0141     0.0000     8.5000 </r>
       <r>    11.0952     0.0000     8.5000 </r>
       <r>    11.1762     0.0000     8.5000 </r>
       <r>    11.2573     0.0000     8.5000 </r>
       <r>    11.3383     0.0000     8.5000 </r>
       <r>    11.4193     0.0000     8.5000 </r>
       <r>    11.5004     0.0000     8.5000 </r>
       <r>    11.5814     0.0000     8.5000 </r>
       <r>    11.6624     0.0000     8.5000 </r>
       <r>    11.7435     0.0000     8.5000 </r>
       <r>    11.8245     0.0000     8.5000 </r>
       <r>    11.9056     0.0000     8.5000 </r>
       <r>    11.9866     0.0000     8.5000 </r>
       <r>    12.0676     0.0000     8.5000 </r>
       <r>    12.1487     0.0000     8.5000 </r>
       <r>    12.2297     0.0000     8.5000 </r>
       <r>    12.3108     0.0000     8.5000 </r>
       <r>    12.3918     0.0000     8.5000 </r>
       <r>    12.4728     0.0005     8.5000 </r>
       <r>    12.5539     0.0042     8.5004 </r>
       <r>    12.6349     0.0278     8.5026 </r>
       <r>    12.7159     0.1335     8.5135 </r>
       <r>    12.7970     0.4702     8.5516 </r>
       <r>    12.8780     1.2185     8.6503 </r>
       <r>    12.9591     2.3448     8.8403 </r>
       <r>    13.0401     3.3926     9.1153 </r>
       <r>    13.1211     3.7491     9.4191 </r>
       <r>    13.2022     3.2151     9.6796 </r>
       <r>    13.2832     2.1617     9.8548 </r>
       <r>    13.3643     1.1395     9.9472 </r>
       <r>    13.4453     0.4659     9.9849 </r>
       <r>    13.5263     0.1460     9.9967 </r>
       <r>    13.6074     0.0390     9.9999 </r>
       <r>    13.6884     0.0373    10.0029 </r>
       <r>    13.7695     0.1461    10.0148 </r>
       <r>    13.8505     0.4896    10.0544 </r>
       <r>    13.9315     1.1971    10.1515 </r>
       <r>    14.0126     2.1266    10.3238 </r>
       <r>    14.0936     2.7463    10.5463 </r>
       <r>    14.1746     2.5906    10.7563 </r>
       <r>    14.2557     1.8464    10.9059 </r>
       <r>    14.3367     1.2177    11.0046 </r>
       <r>    14.4178     1.2568    11.1064 </r>
       <r>    14.4988     1.9304    11.2629 </r>
       <r>    14.5798     2.6429    11.4771 </r>
       <r>    14.6609     2.7146    11.6970 </r>
       <r>    14.7419     2.0346    11.8619 </r>
       <r>    14.8230     1.1084    11.9517 </r>
       <r>    14.9040     0.4387    11.9873 </r>
       <r>    14.9850     0.1261    11.9975 </r>
       <r>    15.0661     0.0263    11.9996 </r>
       <r>    15.1471     0.0040    12.0000 </r>
       <r>    15.2281     0.0004    12.0000 </r>
       <r>    15.3092     0.0000    12.0000 </r>
       <r>    15.3902     0.0000    12.0000 </r>
       <r>    15.4713     0.0000    12.0000 </r>
       <r>    15.5523     0.0001    12.0000 </r>
       <r>    15.6333     0.0008    12.0001 </r>
       <r>    15.7144     0.0068    12.0006 </r>
       <r>    15.7954     0.0417    12.0040 </r>
       <r>    15.8765     0.1846    12.0190 </r>
       <r>    15.9575     0.5997    12.0676 </r>
       <r>    16.0385     1.4423    12.1844 </r>
       <r>    16.1196     2.6213    12.3969 </r>
       <r>    16.2006     3.7242    12.6987 </r>
       <r>    16.2817     4.3203    13.0488 </r>
       <r>    16.3627     4.2228    13.3910 </r>
       <r>    16.4437     3.4580    13.6712 </r>
       <r>    16.5248     2.2846    13.8564 </r>
       <r>    16.6058     1.1674    13.9510 </r>
       <r>    16.6868     0.4477    13.9872 </r>
       <r>    16.7679     0.1267    13.9975 </r>
       <r>    16.8489     0.0264    13.9997 </r>
       <r>    16.9300     0.0056    14.0001 </r>
       <r>    17.0110     0.0138    14.0012 </r>
       <r>    17.0920     0.0774    14.0075 </r>
       <r>    17.1731     0.3290    14.0342 </r>
       <r>    17.2541     1.0316    14.1178 </r>
       <r>    17.3352     2.3934    14.3117 </r>
       <r>    17.4162     4.1198    14.6456 </r>
       <r>    17.4972     5.2717    15.0728 </r>
       <r>    17.5783     5.0198    15.4796 </r>
       <r>    17.6593     3.5562    15.7678 </r>
       <r>    17.7403     1.8718    15.9195 </r>
       <r>    17.8214     0.7304    15.9787 </r>
       <r>    17.9024     0.2106    15.9957 </r>
       <r>    17.9835     0.0448    15.9994 </r>
       <r>    18.0645     0.0070    15.9999 </r>
       <r>    18.1455     0.0008    16.0000 </r>
       <r>    18.2266     0.0001    16.0000 </r>
       <r>    18.3076     0.0000    16.0000 </r>
       <r>    18.3887     0.0000    16.0000 </r>
       <r>    18.4697     0.0000    16.0000 </r>
       <r>    18.5507     0.0000    16.0000 </r>
       <r>    18.6318     0.0000    16.0000 </r>
       <r>    18.7128     0.0000    16.0000 </r>
       <r>    18.7938     0.0000    16.0000 </r>
       <r>    18.8749     0.0000    16.0000 </r>
       <r>    18.9559     0.0000    16.0000 </r>
       <r>    19.0370     0.0000    16.0000 </r>
       <r>    19.1180     0.0000    16.0000 </r>
       <r>    19.1990     0.0000    16.0000 </r>
       <r>    19.2801     0.0000    16.0000 </r>
       <r>    19.3611     0.0000    16.0000 </r>
       <r>    19.4422     0.0000    16.0000 </r>
       <r>    19.5232     0.0000    16.0000 </r>
      </set>
     </set>
    </array>
   </total>
  </dos>
 </calculation>
 <structure name="finalpos" >
  <crystal>
   <varray name="basis" >
    <v>      -2.33682510       2.33682510       1.33337523 </v>
    <v>       2.33682510      -2.33682510       1.33337523 </v>
    <v>       2.33682510       2.33682510      -1.33337523 </v>
   </varray>
   <i name="volume">     29.12492341 </i>
   <varray name="rec_basis" >
    <v>      -0.00000000       0.21396552       0.37498822 </v>
    <v>       0.21396552      -0.00000000       0.37498822 </v>
    <v>       0.21396552       0.21396552       0.00000000 </v>
   </varray>
  </crystal>
  <varray name="positions" >
   <v>       0.25000000       0.75000000       0.50000000 </v>
   <v>      -0.00000000      -0.00000000      -0.00000000 </v>
  </varray>
 </structure>
</modeling>
